{"py/object": "rasa_core.featurizers.MaxHistoryTrackerFeaturizer", "max_history": 5, "remove_duplicates": true, "state_featurizer": {"py/object": "rasa_core.featurizers.BinarySingleStateFeaturizer", "input_state_map": {"entity_change": 21, "entity_food": 20, "entity_number": 22, "entity_ordinal": 23, "intent_None": 0, "intent_ask_order": 1, "intent_cancel": 2, "intent_cancel_answer": 3, "intent_deny": 4, "intent_goodbye": 5, "intent_greet": 6, "intent_kind_answer": 7, "intent_modify_answer": 8, "intent_modify_food": 9, "intent_modify_num": 10, "intent_modify_order": 11, "intent_order_answer": 12, "intent_order_cancel": 13, "intent_order_confirm": 14, "intent_order_meal": 15, "intent_other": 16, "intent_pardon": 17, "intent_telephone_number": 18, "intent_urge_order": 19, "prev_action_again": 37, "prev_action_answer": 44, "prev_action_ask_order": 43, "prev_action_cal_money": 60, "prev_action_cancel": 39, "prev_action_cancel_order": 40, "prev_action_change_food": 57, "prev_action_change_num": 53, "prev_action_check_telephone": 55, "prev_action_deactivate_form": 36, "prev_action_default_fallback": 35, "prev_action_deny_order": 56, "prev_action_greet": 38, "prev_action_listen": 33, "prev_action_modify_order": 58, "prev_action_restart": 34, "prev_action_show_menu": 42, "prev_action_slot_filling": 46, "prev_action_total_money": 59, "prev_action_urge_order": 47, "prev_utter_ask_again": 45, "prev_utter_ask_kind": 54, "prev_utter_bless": 49, "prev_utter_default": 41, "prev_utter_goodbye": 50, "prev_utter_greet": 51, "prev_utter_help": 48, "prev_utter_wait": 52, "slot_fastfood_0": 24, "slot_foodnumber_0": 25, "slot_order_set_0": 26, "slot_order_state_0": 27, "slot_orderform_0": 28, "slot_phone_0": 29, "slot_price_0": 30, "slot_state_0": 31, "slot_user_intent_0": 32}, "num_features": 61, "slot_feature_len": 9, "user_feature_len": 24}, "use_intent_probabilities": false}